medipt/__init__.py
medipt-0.1.dist-info/LICENSE
medipt-0.1.dist-info/METADATA
medipt-0.1.dist-info/WHEEL
medipt-0.1.dist-info/top_level.txt
medipt-0.1.dist-info/RECORD
